{
  "version": 1,
  "cues": [
    {
      "start": 1,
      "end": 3.525,
      "text": "Давайте версионируем ваши repository как",
      "words": [
        { "start": 1, "end": 1.505, "char": [0, 7] },
        { "start": 1.505, "end": 2.01, "char": [8, 20] },
        { "start": 2.01, "end": 2.515, "char": [21, 25] },
        { "start": 2.515, "end": 3.02, "char": [26, 36] },
        { "start": 3.02, "end": 3.525, "char": [37, 40] }
      ]
    },
    {
      "start": 3.525,
      "end": 4.03,
      "text": "код!",
      "words": [{ "start": 3.525, "end": 4.03, "char": [0, 4] }]
    },
    {
      "start": 4.03,
      "end": 6.05,
      "text": "Мы заморозим контрольную точку,",
      "words": [
        { "start": 4.03, "end": 4.535, "char": [0, 2] },
        { "start": 4.535, "end": 5.04, "char": [3, 12] },
        { "start": 5.04, "end": 5.545, "char": [13, 24] },
        { "start": 5.545, "end": 6.05, "char": [25, 31] }
      ]
    },
    {
      "start": 6.05,
      "end": 7.565,
      "text": "дадим ей имя,",
      "words": [
        { "start": 6.05, "end": 6.555, "char": [0, 5] },
        { "start": 6.555, "end": 7.06, "char": [6, 8] },
        { "start": 7.06, "end": 7.565, "char": [9, 13] }
      ]
    },
    {
      "start": 7.565,
      "end": 10.091,
      "text": "а потом удалим настоящую таблицу",
      "words": [
        { "start": 7.565, "end": 8.07, "char": [0, 1] },
        { "start": 8.07, "end": 8.576, "char": [2, 7] },
        { "start": 8.576, "end": 9.081, "char": [8, 14] },
        { "start": 9.081, "end": 9.586, "char": [15, 24] },
        { "start": 9.586, "end": 10.091, "char": [25, 32] }
      ]
    },
    {
      "start": 10.091,
      "end": 11.101,
      "text": "базы данных.",
      "words": [
        { "start": 10.091, "end": 10.596, "char": [0, 4] },
        { "start": 10.596, "end": 11.101, "char": [5, 12] }
      ]
    },
    {
      "start": 11.101,
      "end": 13.626,
      "text": "Rollback возвращает точное замороженное состояние,",
      "words": [
        { "start": 11.101, "end": 11.606, "char": [0, 8] },
        { "start": 11.606, "end": 12.111, "char": [9, 19] },
        { "start": 12.111, "end": 12.616, "char": [20, 26] },
        { "start": 12.616, "end": 13.121, "char": [27, 39] },
        { "start": 13.121, "end": 13.626, "char": [40, 50] }
      ]
    },
    {
      "start": 13.626,
      "end": 15.141,
      "text": "со всеми строками,",
      "words": [
        { "start": 13.626, "end": 14.131, "char": [0, 2] },
        { "start": 14.131, "end": 14.636, "char": [3, 8] },
        { "start": 14.636, "end": 15.141, "char": [9, 18] }
      ]
    },
    {
      "start": 15.141,
      "end": 16.151,
      "text": "за секунды.",
      "words": [
        { "start": 15.141, "end": 15.646, "char": [0, 2] },
        { "start": 15.646, "end": 16.151, "char": [3, 11] }
      ]
    },
    {
      "start": 16.939,
      "end": 18.482,
      "text": "Модель такая же,",
      "words": [
        { "start": 16.939, "end": 17.453, "char": [0, 6] },
        { "start": 17.453, "end": 17.967, "char": [7, 12] },
        { "start": 17.967, "end": 18.482, "char": [13, 16] }
      ]
    },
    {
      "start": 18.482,
      "end": 20.024,
      "text": "как в git,",
      "words": [
        { "start": 18.482, "end": 18.996, "char": [0, 3] },
        { "start": 18.996, "end": 19.51, "char": [4, 5] },
        { "start": 19.51, "end": 20.024, "char": [6, 10] }
      ]
    },
    {
      "start": 20.024,
      "end": 22.081,
      "text": "но для целых repository.",
      "words": [
        { "start": 20.024, "end": 20.538, "char": [0, 2] },
        { "start": 20.538, "end": 21.052, "char": [3, 6] },
        { "start": 21.052, "end": 21.566, "char": [7, 12] },
        { "start": 21.566, "end": 22.081, "char": [13, 24] }
      ]
    },
    {
      "start": 22.081,
      "end": 24.651,
      "text": "Commit это замороженный неизменяемый образ.",
      "words": [
        { "start": 22.081, "end": 22.595, "char": [0, 6] },
        { "start": 22.595, "end": 23.109, "char": [7, 10] },
        { "start": 23.109, "end": 23.623, "char": [11, 23] },
        { "start": 23.623, "end": 24.137, "char": [24, 36] },
        { "start": 24.137, "end": 24.651, "char": [37, 43] }
      ]
    },
    {
      "start": 24.651,
      "end": 26.708,
      "text": "Он даже не монтируется,",
      "words": [
        { "start": 24.651, "end": 25.166, "char": [0, 2] },
        { "start": 25.166, "end": 25.68, "char": [3, 7] },
        { "start": 25.68, "end": 26.194, "char": [8, 10] },
        { "start": 26.194, "end": 26.708, "char": [11, 23] }
      ]
    },
    {
      "start": 26.708,
      "end": 29.279,
      "text": "поэтому ничто не может его",
      "words": [
        { "start": 26.708, "end": 27.222, "char": [0, 7] },
        { "start": 27.222, "end": 27.736, "char": [8, 13] },
        { "start": 27.736, "end": 28.251, "char": [14, 16] },
        { "start": 28.251, "end": 28.765, "char": [17, 22] },
        { "start": 28.765, "end": 29.279, "char": [23, 26] }
      ]
    },
    {
      "start": 29.279,
      "end": 29.793,
      "text": "изменить.",
      "words": [{ "start": 29.279, "end": 29.793, "char": [0, 9] }]
    },
    {
      "start": 29.793,
      "end": 31.85,
      "text": "Branch это просто имя,",
      "words": [
        { "start": 29.793, "end": 30.307, "char": [0, 6] },
        { "start": 30.307, "end": 30.821, "char": [7, 10] },
        { "start": 30.821, "end": 31.336, "char": [11, 17] },
        { "start": 31.336, "end": 31.85, "char": [18, 22] }
      ]
    },
    {
      "start": 31.85,
      "end": 33.392,
      "text": "указывающее на commit.",
      "words": [
        { "start": 31.85, "end": 32.364, "char": [0, 11] },
        { "start": 32.364, "end": 32.878, "char": [12, 14] },
        { "start": 32.878, "end": 33.392, "char": [15, 22] }
      ]
    },
    {
      "start": 33.392,
      "end": 35.963,
      "text": "А checkout превращает любой commit",
      "words": [
        { "start": 33.392, "end": 33.906, "char": [0, 1] },
        { "start": 33.906, "end": 34.421, "char": [2, 10] },
        { "start": 34.421, "end": 34.935, "char": [11, 21] },
        { "start": 34.935, "end": 35.449, "char": [22, 27] },
        { "start": 35.449, "end": 35.963, "char": [28, 34] }
      ]
    },
    {
      "start": 35.963,
      "end": 38.02,
      "text": "в свежий записываемый fork.",
      "words": [
        { "start": 35.963, "end": 36.477, "char": [0, 1] },
        { "start": 36.477, "end": 36.991, "char": [2, 8] },
        { "start": 36.991, "end": 37.506, "char": [9, 21] },
        { "start": 37.506, "end": 38.02, "char": [22, 27] }
      ]
    },
    {
      "start": 41.299,
      "end": 43.871,
      "text": "Наш рабочий fork хранит первую",
      "words": [
        { "start": 41.299, "end": 41.813, "char": [0, 3] },
        { "start": 41.813, "end": 42.328, "char": [4, 11] },
        { "start": 42.328, "end": 42.842, "char": [12, 16] },
        { "start": 42.842, "end": 43.357, "char": [17, 23] },
        { "start": 43.357, "end": 43.871, "char": [24, 30] }
      ]
    },
    {
      "start": 43.871,
      "end": 45.414,
      "text": "версию состояния приложения.",
      "words": [
        { "start": 43.871, "end": 44.385, "char": [0, 6] },
        { "start": 44.385, "end": 44.9, "char": [7, 16] },
        { "start": 44.9, "end": 45.414, "char": [17, 28] }
      ]
    },
    {
      "start": 45.414,
      "end": 47.986,
      "text": "Простой файл-маркер делает её видимой.",
      "words": [
        { "start": 45.414, "end": 45.929, "char": [0, 7] },
        { "start": 45.929, "end": 46.443, "char": [8, 19] },
        { "start": 46.443, "end": 46.958, "char": [20, 26] },
        { "start": 46.958, "end": 47.472, "char": [27, 29] },
        { "start": 47.472, "end": 47.986, "char": [30, 38] }
      ]
    },
    {
      "start": 50.502,
      "end": 51.442,
      "text": "Первая версия,",
      "words": [
        { "start": 50.502, "end": 50.972, "char": [0, 6] },
        { "start": 50.972, "end": 51.442, "char": [7, 14] }
      ]
    },
    {
      "start": 51.442,
      "end": 52.383,
      "text": "на диске.",
      "words": [
        { "start": 51.442, "end": 51.912, "char": [0, 2] },
        { "start": 51.912, "end": 52.383, "char": [3, 9] }
      ]
    },
    {
      "start": 55.679,
      "end": 57.62,
      "text": "Это не просто файлы.",
      "words": [
        { "start": 55.679, "end": 56.164, "char": [0, 3] },
        { "start": 56.164, "end": 56.649, "char": [4, 6] },
        { "start": 56.649, "end": 57.134, "char": [7, 13] },
        { "start": 57.134, "end": 57.62, "char": [14, 20] }
      ]
    },
    {
      "start": 57.62,
      "end": 60.53,
      "text": "В этом fork живёт настоящая база",
      "words": [
        { "start": 57.62, "end": 58.105, "char": [0, 1] },
        { "start": 58.105, "end": 58.59, "char": [2, 6] },
        { "start": 58.59, "end": 59.075, "char": [7, 11] },
        { "start": 59.075, "end": 59.56, "char": [12, 17] },
        { "start": 59.56, "end": 60.045, "char": [18, 27] },
        { "start": 60.045, "end": 60.53, "char": [28, 32] }
      ]
    },
    {
      "start": 60.53,
      "end": 61.501,
      "text": "данных PostgreSQL,",
      "words": [
        { "start": 60.53, "end": 61.015, "char": [0, 6] },
        { "start": 61.015, "end": 61.501, "char": [7, 18] }
      ]
    },
    {
      "start": 61.501,
      "end": 64.411,
      "text": "а таблица customers содержит три строки.",
      "words": [
        { "start": 61.501, "end": 61.986, "char": [0, 1] },
        { "start": 61.986, "end": 62.471, "char": [2, 9] },
        { "start": 62.471, "end": 62.956, "char": [10, 19] },
        { "start": 62.956, "end": 63.441, "char": [20, 28] },
        { "start": 63.441, "end": 63.926, "char": [29, 32] },
        { "start": 63.926, "end": 64.411, "char": [33, 40] }
      ]
    },
    {
      "start": 64.411,
      "end": 65.867,
      "text": "Запомните это число.",
      "words": [
        { "start": 64.411, "end": 64.896, "char": [0, 9] },
        { "start": 64.896, "end": 65.382, "char": [10, 13] },
        { "start": 65.382, "end": 65.867, "char": [14, 20] }
      ]
    },
    {
      "start": 68.367,
      "end": 69.284,
      "text": "Три строки.",
      "words": [
        { "start": 68.367, "end": 68.825, "char": [0, 3] },
        { "start": 68.825, "end": 69.284, "char": [4, 11] }
      ]
    },
    {
      "start": 69.284,
      "end": 72.036,
      "text": "Именно эти данные мы сейчас подвергнем",
      "words": [
        { "start": 69.284, "end": 69.743, "char": [0, 6] },
        { "start": 69.743, "end": 70.201, "char": [7, 10] },
        { "start": 70.201, "end": 70.66, "char": [11, 17] },
        { "start": 70.66, "end": 71.118, "char": [18, 20] },
        { "start": 71.118, "end": 71.577, "char": [21, 27] },
        { "start": 71.577, "end": 72.036, "char": [28, 38] }
      ]
    },
    {
      "start": 72.036,
      "end": 72.494,
      "text": "опасности.",
      "words": [{ "start": 72.036, "end": 72.494, "char": [0, 10] }]
    },
    {
      "start": 75.788,
      "end": 77.008,
      "text": "Заморозьте его.",
      "words": [
        { "start": 75.788, "end": 76.398, "char": [0, 10] },
        { "start": 76.398, "end": 77.008, "char": [11, 15] }
      ]
    },
    {
      "start": 77.008,
      "end": 80.057,
      "text": "Commit фиксирует весь repository как",
      "words": [
        { "start": 77.008, "end": 77.618, "char": [0, 6] },
        { "start": 77.618, "end": 78.228, "char": [7, 16] },
        { "start": 78.228, "end": 78.838, "char": [17, 21] },
        { "start": 78.838, "end": 79.447, "char": [22, 32] },
        { "start": 79.447, "end": 80.057, "char": [33, 36] }
      ]
    },
    {
      "start": 80.057,
      "end": 81.277,
      "text": "неизменяемый образ,",
      "words": [
        { "start": 80.057, "end": 80.667, "char": [0, 12] },
        { "start": 80.667, "end": 81.277, "char": [13, 19] }
      ]
    },
    {
      "start": 81.277,
      "end": 82.497,
      "text": "с сообщением,",
      "words": [
        { "start": 81.277, "end": 81.887, "char": [0, 1] },
        { "start": 81.887, "end": 82.497, "char": [2, 13] }
      ]
    },
    {
      "start": 82.497,
      "end": 84.327,
      "text": "автором и родителем.",
      "words": [
        { "start": 82.497, "end": 83.107, "char": [0, 7] },
        { "start": 83.107, "end": 83.717, "char": [8, 9] },
        { "start": 83.717, "end": 84.327, "char": [10, 20] }
      ]
    },
    {
      "start": 84.327,
      "end": 86.156,
      "text": "Точно как git,",
      "words": [
        { "start": 84.327, "end": 84.937, "char": [0, 5] },
        { "start": 84.937, "end": 85.546, "char": [6, 9] },
        { "start": 85.546, "end": 86.156, "char": [10, 14] }
      ]
    },
    {
      "start": 86.156,
      "end": 87.986,
      "text": "но для всего,",
      "words": [
        { "start": 86.156, "end": 86.766, "char": [0, 2] },
        { "start": 86.766, "end": 87.376, "char": [3, 6] },
        { "start": 87.376, "end": 87.986, "char": [7, 13] }
      ]
    },
    {
      "start": 87.986,
      "end": 89.816,
      "text": "включая базу данных.",
      "words": [
        { "start": 87.986, "end": 88.596, "char": [0, 7] },
        { "start": 88.596, "end": 89.206, "char": [8, 12] },
        { "start": 89.206, "end": 89.816, "char": [13, 20] }
      ]
    },
    {
      "start": 92.816,
      "end": 93.396,
      "text": "Зафиксировано.",
      "words": [{ "start": 92.816, "end": 93.396, "char": [0, 14] }]
    },
    {
      "start": 93.396,
      "end": 96.295,
      "text": "Этот снимок никогда не изменится.",
      "words": [
        { "start": 93.396, "end": 93.976, "char": [0, 4] },
        { "start": 93.976, "end": 94.556, "char": [5, 11] },
        { "start": 94.556, "end": 95.135, "char": [12, 19] },
        { "start": 95.135, "end": 95.715, "char": [20, 22] },
        { "start": 95.715, "end": 96.295, "char": [23, 33] }
      ]
    },
    {
      "start": 96.295,
      "end": 98.615,
      "text": "Он даже не монтируется.",
      "words": [
        { "start": 96.295, "end": 96.875, "char": [0, 2] },
        { "start": 96.875, "end": 97.455, "char": [3, 7] },
        { "start": 97.455, "end": 98.035, "char": [8, 10] },
        { "start": 98.035, "end": 98.615, "char": [11, 23] }
      ]
    },
    {
      "start": 101.926,
      "end": 103.188,
      "text": "Дайте commit имя.",
      "words": [
        { "start": 101.926, "end": 102.347, "char": [0, 5] },
        { "start": 102.347, "end": 102.767, "char": [6, 12] },
        { "start": 102.767, "end": 103.188, "char": [13, 17] }
      ]
    },
    {
      "start": 103.188,
      "end": 105.711,
      "text": "Ветка stable теперь указывает на первую",
      "words": [
        { "start": 103.188, "end": 103.608, "char": [0, 5] },
        { "start": 103.608, "end": 104.029, "char": [6, 12] },
        { "start": 104.029, "end": 104.449, "char": [13, 19] },
        { "start": 104.449, "end": 104.87, "char": [20, 29] },
        { "start": 104.87, "end": 105.291, "char": [30, 32] },
        { "start": 105.291, "end": 105.711, "char": [33, 39] }
      ]
    },
    {
      "start": 105.711,
      "end": 106.132,
      "text": "версию.",
      "words": [{ "start": 105.711, "end": 106.132, "char": [0, 7] }]
    },
    {
      "start": 106.932,
      "end": 108.186,
      "text": "Branch это имя,",
      "words": [
        { "start": 106.932, "end": 107.35, "char": [0, 6] },
        { "start": 107.35, "end": 107.768, "char": [7, 10] },
        { "start": 107.768, "end": 108.186, "char": [11, 15] }
      ]
    },
    {
      "start": 108.186,
      "end": 109.857,
      "text": "к которому можно вернуться.",
      "words": [
        { "start": 108.186, "end": 108.604, "char": [0, 1] },
        { "start": 108.604, "end": 109.022, "char": [2, 10] },
        { "start": 109.022, "end": 109.439, "char": [11, 16] },
        { "start": 109.439, "end": 109.857, "char": [17, 27] }
      ]
    },
    {
      "start": 113.151,
      "end": 114.216,
      "text": "Продолжайте работать.",
      "words": [
        { "start": 113.151, "end": 113.684, "char": [0, 11] },
        { "start": 113.684, "end": 114.216, "char": [12, 21] }
      ]
    },
    {
      "start": 114.216,
      "end": 116.878,
      "text": "Вторая версия заменяет первую в",
      "words": [
        { "start": 114.216, "end": 114.749, "char": [0, 6] },
        { "start": 114.749, "end": 115.281, "char": [7, 13] },
        { "start": 115.281, "end": 115.814, "char": [14, 22] },
        { "start": 115.814, "end": 116.346, "char": [23, 29] },
        { "start": 116.346, "end": 116.878, "char": [30, 31] }
      ]
    },
    {
      "start": 116.878,
      "end": 117.943,
      "text": "рабочем fork.",
      "words": [
        { "start": 116.878, "end": 117.411, "char": [0, 7] },
        { "start": 117.411, "end": 117.943, "char": [8, 13] }
      ]
    },
    {
      "start": 117.943,
      "end": 120.073,
      "text": "Commit это не касается.",
      "words": [
        { "start": 117.943, "end": 118.476, "char": [0, 6] },
        { "start": 118.476, "end": 119.008, "char": [7, 10] },
        { "start": 119.008, "end": 119.541, "char": [11, 13] },
        { "start": 119.541, "end": 120.073, "char": [14, 23] }
      ]
    },
    {
      "start": 122.37,
      "end": 124.433,
      "text": "Рабочий fork двинулся вперёд.",
      "words": [
        { "start": 122.37, "end": 122.885, "char": [0, 7] },
        { "start": 122.885, "end": 123.401, "char": [8, 12] },
        { "start": 123.401, "end": 123.917, "char": [13, 21] },
        { "start": 123.917, "end": 124.433, "char": [22, 29] }
      ]
    },
    {
      "start": 124.433,
      "end": 126.497,
      "text": "История осталась на месте.",
      "words": [
        { "start": 124.433, "end": 124.949, "char": [0, 7] },
        { "start": 124.949, "end": 125.465, "char": [8, 16] },
        { "start": 125.465, "end": 125.981, "char": [17, 19] },
        { "start": 125.981, "end": 126.497, "char": [20, 26] }
      ]
    },
    {
      "start": 129.76,
      "end": 131.496,
      "text": "А теперь катастрофа.",
      "words": [
        { "start": 129.76, "end": 130.339, "char": [0, 1] },
        { "start": 130.339, "end": 130.918, "char": [2, 8] },
        { "start": 130.918, "end": 131.496, "char": [9, 20] }
      ]
    },
    {
      "start": 131.496,
      "end": 134.391,
      "text": "Опасное изменение удаляет таблицу customers.",
      "words": [
        { "start": 131.496, "end": 132.075, "char": [0, 7] },
        { "start": 132.075, "end": 132.654, "char": [8, 17] },
        { "start": 132.654, "end": 133.233, "char": [18, 25] },
        { "start": 133.233, "end": 133.812, "char": [26, 33] },
        { "start": 133.812, "end": 134.391, "char": [34, 44] }
      ]
    },
    {
      "start": 134.391,
      "end": 137.285,
      "text": "В реальной жизни это тот",
      "words": [
        { "start": 134.391, "end": 134.969, "char": [0, 1] },
        { "start": 134.969, "end": 135.548, "char": [2, 10] },
        { "start": 135.548, "end": 136.127, "char": [11, 16] },
        { "start": 136.127, "end": 136.706, "char": [17, 20] },
        { "start": 136.706, "end": 137.285, "char": [21, 24] }
      ]
    },
    {
      "start": 137.285,
      "end": 137.863,
      "text": "момент,",
      "words": [{ "start": 137.285, "end": 137.863, "char": [0, 7] }]
    },
    {
      "start": 137.863,
      "end": 140.758,
      "text": "когда душа уходит в пятки.",
      "words": [
        { "start": 137.863, "end": 138.442, "char": [0, 5] },
        { "start": 138.442, "end": 139.021, "char": [6, 10] },
        { "start": 139.021, "end": 139.6, "char": [11, 17] },
        { "start": 139.6, "end": 140.179, "char": [18, 19] },
        { "start": 140.179, "end": 140.758, "char": [20, 26] }
      ]
    },
    {
      "start": 142.258,
      "end": 143.59,
      "text": "Drop table выполнен.",
      "words": [
        { "start": 142.258, "end": 142.702, "char": [0, 4] },
        { "start": 142.702, "end": 143.146, "char": [5, 10] },
        { "start": 143.146, "end": 143.59, "char": [11, 20] }
      ]
    },
    {
      "start": 143.59,
      "end": 145.81,
      "text": "Данные исчезли из рабочего fork.",
      "words": [
        { "start": 143.59, "end": 144.034, "char": [0, 6] },
        { "start": 144.034, "end": 144.478, "char": [7, 14] },
        { "start": 144.478, "end": 144.922, "char": [15, 17] },
        { "start": 144.922, "end": 145.366, "char": [18, 26] },
        { "start": 145.366, "end": 145.81, "char": [27, 32] }
      ]
    },
    {
      "start": 149.112,
      "end": 150.84,
      "text": "Запросите строки снова,",
      "words": [
        { "start": 149.112, "end": 149.688, "char": [0, 9] },
        { "start": 149.688, "end": 150.264, "char": [10, 16] },
        { "start": 150.264, "end": 150.84, "char": [17, 23] }
      ]
    },
    {
      "start": 150.84,
      "end": 153.721,
      "text": "и база данных ответит прямо:",
      "words": [
        { "start": 150.84, "end": 151.417, "char": [0, 1] },
        { "start": 151.417, "end": 151.993, "char": [2, 6] },
        { "start": 151.993, "end": 152.569, "char": [7, 13] },
        { "start": 152.569, "end": 153.145, "char": [14, 21] },
        { "start": 153.145, "end": 153.721, "char": [22, 28] }
      ]
    },
    {
      "start": 153.721,
      "end": 156.602,
      "text": "relation customers does not exist.",
      "words": [
        { "start": 153.721, "end": 154.297, "char": [0, 8] },
        { "start": 154.297, "end": 154.873, "char": [9, 18] },
        { "start": 154.873, "end": 155.45, "char": [19, 23] },
        { "start": 155.45, "end": 156.026, "char": [24, 27] },
        { "start": 156.026, "end": 156.602, "char": [28, 34] }
      ]
    },
    {
      "start": 156.602,
      "end": 157.754,
      "text": "Катастрофа реальна.",
      "words": [
        { "start": 156.602, "end": 157.178, "char": [0, 10] },
        { "start": 157.178, "end": 157.754, "char": [11, 19] }
      ]
    },
    {
      "start": 157.754,
      "end": 159.483,
      "text": "Каждая строка исчезла.",
      "words": [
        { "start": 157.754, "end": 158.33, "char": [0, 6] },
        { "start": 158.33, "end": 158.906, "char": [7, 13] },
        { "start": 158.906, "end": 159.483, "char": [14, 22] }
      ]
    },
    {
      "start": 161.983,
      "end": 163.968,
      "text": "Relation does not exist.",
      "words": [
        { "start": 161.983, "end": 162.479, "char": [0, 8] },
        { "start": 162.479, "end": 162.975, "char": [9, 13] },
        { "start": 162.975, "end": 163.472, "char": [14, 17] },
        { "start": 163.472, "end": 163.968, "char": [18, 24] }
      ]
    },
    {
      "start": 163.968,
      "end": 165.457,
      "text": "Три строки исчезли.",
      "words": [
        { "start": 163.968, "end": 164.464, "char": [0, 3] },
        { "start": 164.464, "end": 164.961, "char": [4, 10] },
        { "start": 164.961, "end": 165.457, "char": [11, 19] }
      ]
    },
    {
      "start": 168.794,
      "end": 170.775,
      "text": "Зафиксируйте и опасное изменение,",
      "words": [
        { "start": 168.794, "end": 169.289, "char": [0, 12] },
        { "start": 169.289, "end": 169.784, "char": [13, 14] },
        { "start": 169.784, "end": 170.28, "char": [15, 22] },
        { "start": 170.28, "end": 170.775, "char": [23, 33] }
      ]
    },
    {
      "start": 170.775,
      "end": 173.746,
      "text": "с удалённой таблицей и всем прочим.",
      "words": [
        { "start": 170.775, "end": 171.27, "char": [0, 1] },
        { "start": 171.27, "end": 171.765, "char": [2, 11] },
        { "start": 171.765, "end": 172.261, "char": [12, 20] },
        { "start": 172.261, "end": 172.756, "char": [21, 22] },
        { "start": 172.756, "end": 173.251, "char": [23, 27] },
        { "start": 173.251, "end": 173.746, "char": [28, 35] }
      ]
    },
    {
      "start": 173.746,
      "end": 175.232,
      "text": "История записывает то,",
      "words": [
        { "start": 173.746, "end": 174.242, "char": [0, 7] },
        { "start": 174.242, "end": 174.737, "char": [8, 18] },
        { "start": 174.737, "end": 175.232, "char": [19, 22] }
      ]
    },
    {
      "start": 175.232,
      "end": 177.708,
      "text": "что произошло на самом деле.",
      "words": [
        { "start": 175.232, "end": 175.727, "char": [0, 3] },
        { "start": 175.727, "end": 176.223, "char": [4, 13] },
        { "start": 176.223, "end": 176.718, "char": [14, 16] },
        { "start": 176.718, "end": 177.213, "char": [17, 22] },
        { "start": 177.213, "end": 177.708, "char": [23, 28] }
      ]
    },
    {
      "start": 177.708,
      "end": 179.194,
      "text": "Теперь два commit:",
      "words": [
        { "start": 177.708, "end": 178.204, "char": [0, 6] },
        { "start": 178.204, "end": 178.699, "char": [7, 10] },
        { "start": 178.699, "end": 179.194, "char": [11, 18] }
      ]
    },
    {
      "start": 179.194,
      "end": 180.68,
      "text": "родитель и дочерний.",
      "words": [
        { "start": 179.194, "end": 179.689, "char": [0, 8] },
        { "start": 179.689, "end": 180.184, "char": [9, 10] },
        { "start": 180.184, "end": 180.68, "char": [11, 20] }
      ]
    },
    {
      "start": 183.68,
      "end": 185.247,
      "text": "Два снимка в цепочке.",
      "words": [
        { "start": 183.68, "end": 184.072, "char": [0, 3] },
        { "start": 184.072, "end": 184.463, "char": [4, 10] },
        { "start": 184.463, "end": 184.855, "char": [11, 12] },
        { "start": 184.855, "end": 185.247, "char": [13, 21] }
      ]
    },
    {
      "start": 188.549,
      "end": 190.083,
      "text": "И вот история:",
      "words": [
        { "start": 188.549, "end": 189.06, "char": [0, 1] },
        { "start": 189.06, "end": 189.572, "char": [2, 5] },
        { "start": 189.572, "end": 190.083, "char": [6, 14] }
      ]
    },
    {
      "start": 190.083,
      "end": 191.618,
      "text": "вторая версия сверху,",
      "words": [
        { "start": 190.083, "end": 190.595, "char": [0, 6] },
        { "start": 190.595, "end": 191.106, "char": [7, 13] },
        { "start": 191.106, "end": 191.618, "char": [14, 21] }
      ]
    },
    {
      "start": 191.618,
      "end": 193.152,
      "text": "первая под ней,",
      "words": [
        { "start": 191.618, "end": 192.129, "char": [0, 6] },
        { "start": 192.129, "end": 192.641, "char": [7, 10] },
        { "start": 192.641, "end": 193.152, "char": [11, 15] }
      ]
    },
    {
      "start": 193.152,
      "end": 195.198,
      "text": "с сообщениями и авторами,",
      "words": [
        { "start": 193.152, "end": 193.664, "char": [0, 1] },
        { "start": 193.664, "end": 194.175, "char": [2, 13] },
        { "start": 194.175, "end": 194.686, "char": [14, 15] },
        { "start": 194.686, "end": 195.198, "char": [16, 25] }
      ]
    },
    {
      "start": 195.198,
      "end": 197.755,
      "text": "и ни один образ не",
      "words": [
        { "start": 195.198, "end": 195.709, "char": [0, 1] },
        { "start": 195.709, "end": 196.221, "char": [2, 4] },
        { "start": 196.221, "end": 196.732, "char": [5, 9] },
        { "start": 196.732, "end": 197.244, "char": [10, 15] },
        { "start": 197.244, "end": 197.755, "char": [16, 18] }
      ]
    },
    {
      "start": 197.755,
      "end": 198.267,
      "text": "разблокирован.",
      "words": [{ "start": 197.755, "end": 198.267, "char": [0, 14] }]
    },
    {
      "start": 201.267,
      "end": 202.129,
      "text": "Лог repo,",
      "words": [
        { "start": 201.267, "end": 201.698, "char": [0, 3] },
        { "start": 201.698, "end": 202.129, "char": [4, 9] }
      ]
    },
    {
      "start": 202.129,
      "end": 203.853,
      "text": "точно как git log.",
      "words": [
        { "start": 202.129, "end": 202.56, "char": [0, 5] },
        { "start": 202.56, "end": 202.991, "char": [6, 9] },
        { "start": 202.991, "end": 203.422, "char": [10, 13] },
        { "start": 203.422, "end": 203.853, "char": [14, 18] }
      ]
    },
    {
      "start": 207.182,
      "end": 208.786,
      "text": "А теперь награда.",
      "words": [
        { "start": 207.182, "end": 207.717, "char": [0, 1] },
        { "start": 207.717, "end": 208.251, "char": [2, 8] },
        { "start": 208.251, "end": 208.786, "char": [9, 17] }
      ]
    },
    {
      "start": 208.786,
      "end": 211.46,
      "text": "Переключитесь на ветку stable в",
      "words": [
        { "start": 208.786, "end": 209.321, "char": [0, 13] },
        { "start": 209.321, "end": 209.856, "char": [14, 16] },
        { "start": 209.856, "end": 210.39, "char": [17, 22] },
        { "start": 210.39, "end": 210.925, "char": [23, 29] },
        { "start": 210.925, "end": 211.46, "char": [30, 31] }
      ]
    },
    {
      "start": 211.46,
      "end": 213.599,
      "text": "совершенно новый записываемый fork.",
      "words": [
        { "start": 211.46, "end": 211.995, "char": [0, 10] },
        { "start": 211.995, "end": 212.529, "char": [11, 16] },
        { "start": 212.529, "end": 213.064, "char": [17, 29] },
        { "start": 213.064, "end": 213.599, "char": [30, 35] }
      ]
    },
    {
      "start": 213.599,
      "end": 214.134,
      "text": "Reflink-клон:",
      "words": [{ "start": 213.599, "end": 214.134, "char": [0, 13] }]
    },
    {
      "start": 214.134,
      "end": 215.203,
      "text": "почти мгновенно,",
      "words": [
        { "start": 214.134, "end": 214.668, "char": [0, 5] },
        { "start": 214.668, "end": 215.203, "char": [6, 16] }
      ]
    },
    {
      "start": 215.203,
      "end": 216.273,
      "text": "любого размера.",
      "words": [
        { "start": 215.203, "end": 215.738, "char": [0, 6] },
        { "start": 215.738, "end": 216.273, "char": [7, 15] }
      ]
    },
    {
      "start": 219.273,
      "end": 221.807,
      "text": "Записываемая копия замороженной первой",
      "words": [
        { "start": 219.273, "end": 219.906, "char": [0, 12] },
        { "start": 219.906, "end": 220.54, "char": [13, 18] },
        { "start": 220.54, "end": 221.173, "char": [19, 31] },
        { "start": 221.173, "end": 221.807, "char": [32, 38] }
      ]
    },
    {
      "start": 221.807,
      "end": 222.44,
      "text": "версии,",
      "words": [{ "start": 221.807, "end": 222.44, "char": [0, 7] }]
    },
    {
      "start": 222.44,
      "end": 224.34,
      "text": "примерно за секунду.",
      "words": [
        { "start": 222.44, "end": 223.073, "char": [0, 8] },
        { "start": 223.073, "end": 223.707, "char": [9, 11] },
        { "start": 223.707, "end": 224.34, "char": [12, 20] }
      ]
    },
    {
      "start": 227.667,
      "end": 230.242,
      "text": "Запустите rollback fork как любой другой",
      "words": [
        { "start": 227.667, "end": 228.096, "char": [0, 9] },
        { "start": 228.096, "end": 228.525, "char": [10, 18] },
        { "start": 228.525, "end": 228.954, "char": [19, 23] },
        { "start": 228.954, "end": 229.384, "char": [24, 27] },
        { "start": 229.384, "end": 229.813, "char": [28, 33] },
        { "start": 229.813, "end": 230.242, "char": [34, 40] }
      ]
    },
    {
      "start": 230.242,
      "end": 230.671,
      "text": "repo.",
      "words": [{ "start": 230.242, "end": 230.671, "char": [0, 5] }]
    },
    {
      "start": 238.194,
      "end": 239.713,
      "text": "Два fork запущены:",
      "words": [
        { "start": 238.194, "end": 238.701, "char": [0, 3] },
        { "start": 238.701, "end": 239.207, "char": [4, 8] },
        { "start": 239.207, "end": 239.713, "char": [9, 18] }
      ]
    },
    {
      "start": 239.713,
      "end": 242.243,
      "text": "текущая версия и контрольная точка.",
      "words": [
        { "start": 239.713, "end": 240.219, "char": [0, 7] },
        { "start": 240.219, "end": 240.725, "char": [8, 14] },
        { "start": 240.725, "end": 241.231, "char": [15, 16] },
        { "start": 241.231, "end": 241.737, "char": [17, 28] },
        { "start": 241.737, "end": 242.243, "char": [29, 35] }
      ]
    },
    {
      "start": 245.507,
      "end": 247.222,
      "text": "И вот доказательство:",
      "words": [
        { "start": 245.507, "end": 246.079, "char": [0, 1] },
        { "start": 246.079, "end": 246.65, "char": [2, 5] },
        { "start": 246.65, "end": 247.222, "char": [6, 21] }
      ]
    },
    {
      "start": 247.222,
      "end": 250.08,
      "text": "rollback fork читает первую версию.",
      "words": [
        { "start": 247.222, "end": 247.794, "char": [0, 8] },
        { "start": 247.794, "end": 248.365, "char": [9, 13] },
        { "start": 248.365, "end": 248.937, "char": [14, 20] },
        { "start": 248.937, "end": 249.508, "char": [21, 27] },
        { "start": 249.508, "end": 250.08, "char": [28, 35] }
      ]
    },
    {
      "start": 250.08,
      "end": 252.938,
      "text": "Рабочий fork по-прежнему содержит вторую.",
      "words": [
        { "start": 250.08, "end": 250.652, "char": [0, 7] },
        { "start": 250.652, "end": 251.223, "char": [8, 12] },
        { "start": 251.223, "end": 251.795, "char": [13, 24] },
        { "start": 251.795, "end": 252.366, "char": [25, 33] },
        { "start": 252.366, "end": 252.938, "char": [34, 41] }
      ]
    },
    {
      "start": 252.938,
      "end": 253.51,
      "text": "История,",
      "words": [{ "start": 252.938, "end": 253.51, "char": [0, 8] }]
    },
    {
      "start": 253.51,
      "end": 255.225,
      "text": "которую можно запустить.",
      "words": [
        { "start": 253.51, "end": 254.081, "char": [0, 7] },
        { "start": 254.081, "end": 254.653, "char": [8, 13] },
        { "start": 254.653, "end": 255.225, "char": [14, 24] }
      ]
    },
    {
      "start": 256.725,
      "end": 257.778,
      "text": "Rollback завершён.",
      "words": [
        { "start": 256.725, "end": 257.251, "char": [0, 8] },
        { "start": 257.251, "end": 257.778, "char": [9, 18] }
      ]
    },
    {
      "start": 257.778,
      "end": 259.885,
      "text": "Ничего не было перезаписано.",
      "words": [
        { "start": 257.778, "end": 258.305, "char": [0, 6] },
        { "start": 258.305, "end": 258.832, "char": [7, 9] },
        { "start": 258.832, "end": 259.359, "char": [10, 14] },
        { "start": 259.359, "end": 259.885, "char": [15, 28] }
      ]
    },
    {
      "start": 263.198,
      "end": 264.591,
      "text": "И самое главное:",
      "words": [
        { "start": 263.198, "end": 263.662, "char": [0, 1] },
        { "start": 263.662, "end": 264.127, "char": [2, 7] },
        { "start": 264.127, "end": 264.591, "char": [8, 16] }
      ]
    },
    {
      "start": 264.591,
      "end": 267.378,
      "text": "удалённая таблица вернулась со всеми тремя",
      "words": [
        { "start": 264.591, "end": 265.056, "char": [0, 9] },
        { "start": 265.056, "end": 265.52, "char": [10, 17] },
        { "start": 265.52, "end": 265.984, "char": [18, 27] },
        { "start": 265.984, "end": 266.449, "char": [28, 30] },
        { "start": 266.449, "end": 266.913, "char": [31, 36] },
        { "start": 266.913, "end": 267.378, "char": [37, 42] }
      ]
    },
    {
      "start": 267.378,
      "end": 267.842,
      "text": "строками.",
      "words": [{ "start": 267.378, "end": 267.842, "char": [0, 9] }]
    },
    {
      "start": 267.842,
      "end": 269.7,
      "text": "Rollback восстановил базу данных,",
      "words": [
        { "start": 267.842, "end": 268.306, "char": [0, 8] },
        { "start": 268.306, "end": 268.771, "char": [9, 20] },
        { "start": 268.771, "end": 269.235, "char": [21, 25] },
        { "start": 269.235, "end": 269.7, "char": [26, 33] }
      ]
    },
    {
      "start": 269.7,
      "end": 271.557,
      "text": "а не только файлы.",
      "words": [
        { "start": 269.7, "end": 270.164, "char": [0, 1] },
        { "start": 270.164, "end": 270.628, "char": [2, 4] },
        { "start": 270.628, "end": 271.093, "char": [5, 11] },
        { "start": 271.093, "end": 271.557, "char": [12, 18] }
      ]
    },
    {
      "start": 274.716,
      "end": 277.036,
      "text": "Снова три строки.",
      "words": [
        { "start": 274.716, "end": 275.489, "char": [0, 5] },
        { "start": 275.489, "end": 276.262, "char": [6, 9] },
        { "start": 276.262, "end": 277.036, "char": [10, 17] }
      ]
    },
    {
      "start": 277.036,
      "end": 278.582,
      "text": "Катастрофа отменена.",
      "words": [
        { "start": 277.036, "end": 277.809, "char": [0, 10] },
        { "start": 277.809, "end": 278.582, "char": [11, 20] }
      ]
    },
    {
      "start": 293.575,
      "end": 296.012,
      "text": "Commit-ы никогда не меняются,",
      "words": [
        { "start": 293.575, "end": 294.184, "char": [0, 8] },
        { "start": 294.184, "end": 294.793, "char": [9, 16] },
        { "start": 294.793, "end": 295.403, "char": [17, 19] },
        { "start": 295.403, "end": 296.012, "char": [20, 29] }
      ]
    },
    {
      "start": 296.012,
      "end": 298.448,
      "text": "fork-и никогда не ждут.",
      "words": [
        { "start": 296.012, "end": 296.621, "char": [0, 6] },
        { "start": 296.621, "end": 297.23, "char": [7, 14] },
        { "start": 297.23, "end": 297.839, "char": [15, 17] },
        { "start": 297.839, "end": 298.448, "char": [18, 23] }
      ]
    },
    {
      "start": 298.448,
      "end": 299.667,
      "text": "Следующий шаг:",
      "words": [
        { "start": 298.448, "end": 299.058, "char": [0, 9] },
        { "start": 299.058, "end": 299.667, "char": [10, 14] }
      ]
    },
    {
      "start": 299.667,
      "end": 302.713,
      "text": "мы перемещаем весь работающий repository",
      "words": [
        { "start": 299.667, "end": 300.276, "char": [0, 2] },
        { "start": 300.276, "end": 300.885, "char": [3, 13] },
        { "start": 300.885, "end": 301.494, "char": [14, 18] },
        { "start": 301.494, "end": 302.103, "char": [19, 29] },
        { "start": 302.103, "end": 302.713, "char": [30, 40] }
      ]
    },
    {
      "start": 302.713,
      "end": 304.54,
      "text": "на другую машину,",
      "words": [
        { "start": 302.713, "end": 303.322, "char": [0, 2] },
        { "start": 303.322, "end": 303.931, "char": [3, 9] },
        { "start": 303.931, "end": 304.54, "char": [10, 17] }
      ]
    },
    {
      "start": 304.54,
      "end": 306.368,
      "text": "в реальном времени.",
      "words": [
        { "start": 304.54, "end": 305.149, "char": [0, 1] },
        { "start": 305.149, "end": 305.759, "char": [2, 10] },
        { "start": 305.759, "end": 306.368, "char": [11, 19] }
      ]
    },
    {
      "start": 306.368,
      "end": 308.804,
      "text": "Увидимся в следующем уроке!",
      "words": [
        { "start": 306.368, "end": 306.977, "char": [0, 8] },
        { "start": 306.977, "end": 307.586, "char": [9, 10] },
        { "start": 307.586, "end": 308.195, "char": [11, 20] },
        { "start": 308.195, "end": 308.804, "char": [21, 27] }
      ]
    }
  ]
}
